claudewarp/__init__.py
claudewarp/cli/__init__.py
claudewarp/cli/commands.py
claudewarp/cli/formatters.py
claudewarp/cli/main.py
claudewarp/core/__init__.py
claudewarp/core/config.py
claudewarp/core/exceptions.py
claudewarp/core/manager.py
claudewarp/core/models.py
claudewarp/core/utils.py
claudewarp_cli-0.0.35.dist-info/METADATA
claudewarp_cli-0.0.35.dist-info/WHEEL
claudewarp_cli-0.0.35.dist-info/entry_points.txt
claudewarp_cli-0.0.35.dist-info/licenses/LICENSE
claudewarp_cli-0.0.35.dist-info/RECORD
