Metadata-Version: 2.4
Name: claudewarp_cli
Version: 0.0.35
Summary: Claude API proxy management tool with CLI
Project-URL: Homepage, https://github.com/yourname/claudewarp
Project-URL: Repository, https://github.com/yourname/claudewarp
Project-URL: Issues, https://github.com/yourname/claudewarp/issues
Project-URL: Documentation, https://github.com/yourname/claudewarp#readme
Author-email: ClaudeWarp Team <team@claudewarp.dev>
License-Expression: MIT
License-File: LICENSE
Keywords: api,claude,cli,management,proxy
Classifier: Development Status :: 3 - Alpha
Classifier: Intended Audience :: Developers
Classifier: License :: OSI Approved :: MIT License
Classifier: Operating System :: OS Independent
Classifier: Programming Language :: Python :: 3
Classifier: Programming Language :: Python :: 3.8
Classifier: Programming Language :: Python :: 3.9
Classifier: Programming Language :: Python :: 3.10
Classifier: Programming Language :: Python :: 3.11
Classifier: Programming Language :: Python :: 3.12
Classifier: Topic :: Software Development :: Libraries :: Python Modules
Classifier: Topic :: Utilities
Requires-Python: >=3.8
Requires-Dist: colorlog>=6.0.0
Requires-Dist: pydantic<3.0.0,>=2.0.0
Requires-Dist: rich>=13.0.0
Requires-Dist: toml>=0.10.0
Requires-Dist: typer>=0.16.0
